codetide/__init__.py
codetide/autocomplete.py
codetide/core/__init__.py
codetide/core/common.py
codetide/core/defaults.py
codetide/core/html.py
codetide/core/logs.py
codetide/core/mermaid.py
codetide/core/models.py
codetide/parsers/__init__.py
codetide/parsers/base_parser.py
codetide/parsers/generic_parser.py
codetide/parsers/python_parser.py
codetide/parsers/typescript_parser.py
codetide-0.0.21.dist-info/licenses/LICENSE
codetide-0.0.21.dist-info/METADATA
codetide-0.0.21.dist-info/WHEEL
codetide-0.0.21.dist-info/entry_points.txt
codetide-0.0.21.dist-info/top_level.txt
codetide-0.0.21.dist-info/RECORD
