Metadata-Version: 2.4
Name: codetide
Version: 0.0.21
Classifier: Programming Language :: Python :: 3.10
Classifier: Programming Language :: Python :: 3.11
Classifier: Programming Language :: Python :: 3.12
Classifier: Programming Language :: Python :: 3.13
Classifier: License :: OSI Approved :: Apache Software License
Classifier: Operating System :: OS Independent
License-File: LICENSE
Requires-Dist: loguru==0.7.3
Requires-Dist: pathspec==0.12.1
Requires-Dist: pydantic==2.10.3
Requires-Dist: pygit2==1.18.0
Requires-Dist: pyyaml==6.0.2
Requires-Dist: tree-sitter==0.24.0
Requires-Dist: tree-sitter-python==0.23.6
Requires-Dist: tree-sitter-typescript==0.23.2
Provides-Extra: visualization
Requires-Dist: plotly==5.24.1; extra == "visualization"
Requires-Dist: networkx==3.4.2; extra == "visualization"
Requires-Dist: numpy==2.2.0; extra == "visualization"
Dynamic: classifier
Dynamic: description
Dynamic: description-content-type
Dynamic: license-file
Dynamic: provides-extra
Dynamic: requires-dist
